{
  "__type": "USeDirect.RDClasses.Availability.AdvanceUnitAvailabilityWeb",
  "PlaceId": 740,
  "RegionName": "Marlborough",
  "FacilityId": 2454,
  "PlaceName": "Momorangi Bay Campground",
  "FacilityName": "Cabins",
  "UnitTypeId": 111,
  "UnitTypeName": "Entire room",
  "Count": 2,
  "CategoryId": 0,
  "Tentsite": 0,
  "Rcsite": 0,
  "Vehiclelength": 0,
  "Searchlevel": 0,
  "UnitIsFilter": false,
  "FilteredApplied": 1,
  "EnterpriseShortName": "NewZealand",
  "FacilityAlert": false,
  "SiteUrl": "https://bookings.doc.govt.nz/Web/",
  "FacilityTypeNew": 2,
  "FacilitySeasonInfo": "Basic cabin with double bunk bed suitable for 1 or 2 people. Bring own linen. Users share camp kitchen, shower and toilet blocks with other campers.",
  "IsAda": false,
  "IncludeADAWaitlistNotification": true,
  "FacilityAllowWebBooking": true
}